ifdo/__init__.py
ifdo/models/__init__.py
ifdo/models/_kebab_case_model.py
ifdo/models/ifdo.py
ifdo/models/ifdo_capture.py
ifdo/models/ifdo_content.py
ifdo/models/ifdo_core.py
ifdo-1.3.0.dist-info/licenses/LICENSE
ifdo-1.3.0.dist-info/METADATA
ifdo-1.3.0.dist-info/WHEEL
ifdo-1.3.0.dist-info/top_level.txt
ifdo-1.3.0.dist-info/RECORD
