Metadata-Version: 2.4
Name: ifdo
Version: 1.3.0
Summary: Python iFDO implementation
Author-email: Kevin Barnard <kbarnard@mbari.org>, Chris Jackett <chris.jackett@csiro.au>, Karsten Schimpf <karsten.schimpf@awi.de>
License: MIT
Requires-Python: >=3.10
License-File: LICENSE
Requires-Dist: pyyaml<7.0,>=6.0
Requires-Dist: pydantic<3.0.0,>=2.4.2
Dynamic: license-file
